deeprecsys/__init__.py
deeprecsys/neural_networks/base_network.py
deeprecsys/neural_networks/binary_classifier.py
deeprecsys/neural_networks/deep_q_network.py
deeprecsys/neural_networks/dueling.py
deeprecsys/neural_networks/gaussian_actor.py
deeprecsys/neural_networks/noisy_layer.py
deeprecsys/neural_networks/policy_estimator.py
deeprecsys/neural_networks/q_value_estimator.py
deeprecsys/neural_networks/value_estimator.py
deeprecsys/rl/__init__.py
deeprecsys/rl/agents/actor_critic.py
deeprecsys/rl/agents/agent.py
deeprecsys/rl/agents/dqn.py
deeprecsys/rl/agents/epsilon_greedy.py
deeprecsys/rl/agents/rainbow.py
deeprecsys/rl/agents/reinforce.py
deeprecsys/rl/agents/soft_actor_critic.py
deeprecsys/rl/experience_replay/buffer_parameters.py
deeprecsys/rl/experience_replay/experience_buffer.py
deeprecsys/rl/experience_replay/priority_replay_buffer.py
deeprecsys/rl/learning_statistics.py
deeprecsys/rl/manager.py
deeprecsys-0.2.7.dist-info/LICENSE
deeprecsys-0.2.7.dist-info/METADATA
deeprecsys-0.2.7.dist-info/WHEEL
deeprecsys-0.2.7.dist-info/RECORD
