Metadata-Version: 2.1
Name: deeprecsys
Version: 0.2.7
Summary: deeprecsys is an open tool belt to speed up the development of modern data science projects at an enterprise level
Home-page: https://deeprecsys.com
License: GPL-3.0-or-later
Keywords: machinelearning,reinforcementlearning,recommmendersystems,deeplearning,datascience
Author: Lucas Farris
Author-email: lucas@farris.com.br
Requires-Python: >=3.9,<4
Classifier: License :: OSI Approved :: GNU General Public License v3 or later (GPLv3+)
Classifier: Programming Language :: Python :: 3
Classifier: Programming Language :: Python :: 3.9
Classifier: Programming Language :: Python :: 3.10
Classifier: Programming Language :: Python :: 3.11
Classifier: Programming Language :: Python :: 3.12
Classifier: Topic :: Scientific/Engineering :: Artificial Intelligence
Provides-Extra: recsys
Requires-Dist: gymnasium (>=0.29.1,<0.30.0) ; extra == "recsys"
Requires-Dist: highway-env (>=1.8.2,<2.0.0) ; extra == "recsys"
Requires-Dist: keras (>=3.3.3,<4.0.0) ; extra == "recsys"
Requires-Dist: pandas (>=2.2.2,<3.0.0)
Requires-Dist: pyarrow (>=16.1.0,<17.0.0)
Requires-Dist: seaborn (>=0.13.2,<0.14.0)
Requires-Dist: tensorboard (>=2.16.2,<3.0.0) ; extra == "recsys"
Requires-Dist: torch (==2.3.0+cpu) ; extra == "recsys"
Requires-Dist: torchviz (>=0.0.2,<0.0.3) ; extra == "recsys"
Project-URL: Documentation, https://deeprecsys.com
Project-URL: Repository, https://github.com/luksfarris/deeprecsys
